LICENSE
README.md
signal_webhooks/__init__.py
signal_webhooks/admin.py
signal_webhooks/api/__init__.py
signal_webhooks/api/serializers.py
signal_webhooks/api/views.py
signal_webhooks/apps.py
signal_webhooks/exceptions.py
signal_webhooks/fields.py
signal_webhooks/handlers.py
signal_webhooks/migrations/0001_initial.py
signal_webhooks/migrations/0002_change_auth_token_and_last_response_max_length.py
signal_webhooks/migrations/0003_alter_webhook_endpoint_alter_webhook_name_and_more.py
signal_webhooks/migrations/0004_migrate_signal_choices.py
signal_webhooks/migrations/__init__.py
signal_webhooks/models.py
signal_webhooks/py.typed
signal_webhooks/serializers.py
signal_webhooks/settings.py
signal_webhooks/typing.py
signal_webhooks/utils.py
django_signal_webhooks-0.3.1.dist-info/LICENSE
django_signal_webhooks-0.3.1.dist-info/METADATA
django_signal_webhooks-0.3.1.dist-info/WHEEL
django_signal_webhooks-0.3.1.dist-info/RECORD
