Metadata-Version: 2.1
Name: django-signal-webhooks
Version: 0.3.1
Summary: Add webhooks to django using signals.
Home-page: https://mrthearman.github.io/django-signal-webhooks/
License: MIT
Keywords: django,signal,webhooks
Author: Matti Lamppu
Author-email: lamppu.matti.akseli@gmail.com
Requires-Python: >=3.9,<4
Classifier: Environment :: Web Environment
Classifier: Framework :: Django
Classifier: Framework :: Django :: 4.2
Classifier: Framework :: Django :: 5.0
Classifier: Framework :: Django :: 5.1
Classifier: Intended Audience :: Developers
Classifier: License :: OSI Approved :: MIT License
Classifier: Natural Language :: English
Classifier: Operating System :: OS Independent
Classifier: Programming Language :: Python
Classifier: Programming Language :: Python :: 3
Classifier: Programming Language :: Python :: 3.9
Classifier: Programming Language :: Python :: 3.10
Classifier: Programming Language :: Python :: 3.11
Classifier: Programming Language :: Python :: 3.12
Classifier: Programming Language :: Python :: 3 :: Only
Classifier: Programming Language :: Python :: 3.13
Provides-Extra: drf
Requires-Dist: Django (>=4.2)
Requires-Dist: asgiref (>=3.5.0)
Requires-Dist: cryptography (>=43.0.0)
Requires-Dist: django-settings-holder (>=0.2.1)
Requires-Dist: djangorestframework (>=3.14.0) ; extra == "drf"
Requires-Dist: httpx (>=0.23.0)
Requires-Dist: typing-extensions (>=4.12.1) ; python_version < "3.11"
Project-URL: Bug Tracker, https://github.com/MrThearMan/django-signal-webhooks/issues
Project-URL: Repository, https://github.com/MrThearMan/django-signal-webhooks
